setup.py
sonosalarm/__init__.py
sonosalarm/alarm.py
sonosalarm/cli.py
sonosalarm/discovery.py
sonosalarm/helpers.py
sonosalarm.egg-info/PKG-INFO
sonosalarm.egg-info/SOURCES.txt
sonosalarm.egg-info/dependency_links.txt
sonosalarm.egg-info/entry_points.txt
sonosalarm.egg-info/not-zip-safe
sonosalarm.egg-info/requires.txt
sonosalarm.egg-info/top_level.txt