Metadata-Version: 1.1
Name: sonosalarm
Version: 0.2.0
Summary: Sane alarm player for Sonos
Home-page: https://www.codedog.co.uk/sonosalarm
Author: Sam Rudge
Author-email: sam@codesam.co.uk
License: MIT
Platform: UNKNOWN
Classifier: Development Status :: 4 - Beta
Classifier: Environment :: Console
Classifier: License :: OSI Approved :: MIT License
Classifier: Programming Language :: Python
Classifier: Topic :: Home Automation
Classifier: Topic :: Multimedia :: Sound/Audio
Classifier: Programming Language :: Python :: 3
Classifier: Programming Language :: Python :: 3.5
